ej2/Mealy2/src/clock.v
`timescale 1us / 1us
module clock_gen(clk);

parameter PERIOD = 10;

output reg clk;
	 
always
	begin: CLOCK_DRIVER
		clk <= 1'b0;
		#(PERIOD/2);
		clk <= 1'b1;
		#(PERIOD/2);
	end
endmodule

ej3/Mealy3/src/RisingEdgeFlipFlopD.v
//Modulo que simula el comportamiento de un flip flop D
//,de flancos ascedentes,con reset asincronico
module RisingEdgeFlipFlopD(
D,
Q,
clk,
reset_n
);

input D; // Data input 
input clk; // clock input 
input reset_n; //reset input
output reg Q; // output Q 
always @(posedge clk) 
begin
 Q <= D; 
end 

always @(reset_n) //Si reset_n es 0, pone en cero la salida del flip flop
    if (~reset_n) begin
      Q<=0;
    end

endmodule

ej2/Mealy2/src/logica_comb_de_salida.v
//Modulo que se encarga de la logica combinacional del bloque
//de salida de la maquina de estados.
//Este es el bloque que define cual va a ser la salida
//de la FSM en base al estado actual y al bit de input.
module logica_comb_de_salida(
    w,
    y1,
    y2,
    z
);

input w;
input y1;
input y2;
output z;

wire a;
nand (a,w,y1,y2);
nand (z,a,a); //La salida es el and de las tres entradas.

endmodule

ej2/Mealy2/src/logica_comb_de_entrada.v
//Modulo que se encarga de la logica combinacional del bloque
//de entrada de la maquina de estados.
//Este es el bloque que define cual va a ser el proximo estado
//de la FSM en base al estado actual y al bit ingesado como input.
module logica_comb_de_entrada(
    w,
    y1,
    y2,
    Yout1,
    Yout2
);

input w;
input y1;
input y2;
output Yout1;
output Yout2;

wire a,b,c,d,e,f,g,h,i;
nand (a,w,w); //Utilizo una nand como not, niego w.
nand (b,y1,y1); //niego y1.
nand (c,y2,y2); //niego y2.

nand (d, b, w,y2);
nand (e, a, y1, c);
nand (Yout1,d,e); //Salida correspondiente a la primera variable de estado.

nand (f, w, b, c);
nand (g, a, y1, c);
nand (Yout2, f, g); //Salida correspondiente a la segunda variable de estado.


endmodule

ej2/Mealy2/src/DetectorDeSecuencia.v
//Modulo que simula el control de una mquina
//de estados que reconoce en forma sincronica
//la secuencia de 4 bits 1-1-0-1.
module DetectorDeSecuencia(
    w,
    z,
    clk,
    reset_n
);
input clk; //Entrada de clock
input reset_n; //Entrada de reset
input w; //bit detectado.
output z;
wire a;
wire estado_actual1;
wire estado_actual2;
wire prox_estado1;
wire prox_estado2;
//Etapa de la logicca de entrada
logica_comb_de_entrada primer_bloque(w,estado_actual1, estado_actual2,prox_estado1,prox_estado2);
//Etapa de flip-flops donde se guarda el estado actual.
RisingEdgeFlipFlopD f1(prox_estado1,estado_actual1,clk,reset_n);
RisingEdgeFlipFlopD f2(prox_estado2,estado_actual2,clk,reset_n);
//Etapa de la logica de salida
logica_comb_de_salida segundo_bloque(w,estado_actual1,estado_actual2,a);
RisingEdgeFlipFlopD f3(a,z,clk,reset_n); //Flip flop a la salida para asegurar que
                                        //el output sea sincronico.

endmodule

Mealy2/src/DetectorDeSecuencia_tb.v
//Testbench correspondiente a la FSM que implementa el detector
//de la secuencia de 4 bits 1-1-0-1.
`timescale 10us / 1us

module DetectorDeSecuencia_tb;

wire clk;
reg reset_n;
reg w;
wire z;
DetectorDeSecuencia inst(w,z,clk,reset_n);
clock_gen clk_gen(clk);

initial begin
    reset_n=0; //Pongo la FSM en su estado incial
    w=0;
    #1
    reset_n=1;
    #1
    w=1;
    #2
    w=0;
    #1
    w=1;
    #3
    w=0;
    #2
    $finish;

end

reg dummy;
  reg[8*64:0] dumpfile_path = "output.vcd";

  initial begin
    dummy = $value$plusargs("VCD_PATH=%s", dumpfile_path);
    $dumpfile(dumpfile_path);
    $dumpvars(0,DetectorDeSecuencia_tb);
  end


endmodule

ej2/Mealy2/bin/output.vcd
$date
	Sun Nov  4 13:11:50 2018
$end
$version
	Icarus Verilog
$end
$timescale
	1us
$end
$scope module DetectorDeSecuencia_tb $end
$var wire 1 ! clk $end
$var wire 1 " z $end
$var reg 1 # dummy $end
$var reg 513 $ dumpfile_path [512:0] $end
$var reg 1 % reset_n $end
$var reg 1 & w $end
$scope module inst $end
$var wire 1 ' a $end
$var wire 1 ! clk $end
$var wire 1 ( estado_actual1 $end
$var wire 1 ) estado_actual2 $end
$var wire 1 * prox_estado1 $end
$var wire 1 + prox_estado2 $end
$var wire 1 , reset_n $end
$var wire 1 - w $end
$var wire 1 " z $end
$scope module primer_bloque $end
$var wire 1 * Yout1 $end
$var wire 1 + Yout2 $end
$var wire 1 . a $end
$var wire 1 / b $end
$var wire 1 0 c $end
$var wire 1 1 d $end
$var wire 1 2 e $end
$var wire 1 3 f $end
$var wire 1 4 g $end
$var wire 1 - w $end
$var wire 1 ( y1 $end
$var wire 1 ) y2 $end
$upscope $end
$scope module f1 $end
$var wire 1 * D $end
$var wire 1 ! clk $end
$var wire 1 , reset_n $end
$var reg 1 5 Q $end
$upscope $end
$scope module f2 $end
$var wire 1 + D $end
$var wire 1 ! clk $end
$var wire 1 , reset_n $end
$var reg 1 6 Q $end
$upscope $end
$scope module segundo_bloque $end
$var wire 1 7 a $end
$var wire 1 - w $end
$var wire 1 ( y1 $end
$var wire 1 ) y2 $end
$var wire 1 ' z $end
$upscope $end
$scope module f3 $end
$var wire 1 ' D $end
$var wire 1 ! clk $end
$var wire 1 , reset_n $end
$var reg 1 8 Q $end
$upscope $end
$upscope $end
$scope module clk_gen $end
$var reg 1 9 clk $end
$scope begin CLOCK_DRIVER $end
$upscope $end
$upscope $end
$upscope $end
$enddefinitions $end
#0
$dumpvars
09
08
17
06
05
14
13
12
11
10
1/
1.
0-
0,
0+
0*
0)
0(
0'
0&
0%
b110001001101001011011100010111101101111011101010111010001110000011101010111010000101110011101100110001101100100 $
1#
0"
0!
$end
#5
19
1!
#10
09
0!
1%
1,
#15
19
1!
#20
09
0!
1+
0.
03
1&
1-
#25
0+
1*
13
01
00
16
1)
19
1!
#30
09
0!
#35
0*
11
10
0/
06
0)
15
1(
19
1!
#40
09
0!
1*
1+
02
04
1.
0&
0-
#45
0*
0+
12
14
00
16
1)
19
1!
#50
09
0!
1'
0.
07
1&
1-
#55
1+
0'
03
10
17
1/
18
1"
06
0)
05
0(
19
1!
#60
09
0!
#65
0+
1*
13
01
00
16
1)
08
0"
19
1!
#70
09
0!
#75
0*
11
10
0/
06
0)
15
1(
19
1!
#80
09
0!
1*
1+
02
04
1.
0&
0-
#85
0*
0+
12
14
00
16
1)
19
1!
#90
09
0!
#95
10
1/
06
0)
05
0(
19
1!
