ej3/Moore3/Moore/clock.v
`timescale 100us/100us

module clock_gen(clk);

	parameter PERIOD = 10;

	output reg clk;
		
	always
		begin: CLOCK_DRIVER
			clk <= 1'b0;
			#(PERIOD/2);
			clk <= 1'b1;
			#(PERIOD/2);
		end

endmodule

ej3/Mealy3/src/logica_comb_de_salida.v
//Modulo que se encarga de la logica combinacional del bloque
//de salida de la maquina de estados.
//Este es el bloque que define cual va a ser la salida
//de la FSM en base al estado actual y al input.
module logica_comb_de_salida(
    w,
    y,
    z
);

input w;
input y;
output z;
wire a,b,c,d;
nand (a,y,y); //Niego y
nand(b,a,w);
nand(z,b,b); //La salida es el and de ~y con w.

endmodule

ej3/Mealy3/src/RisingEdgeFlipFlopD.v
//Modulo que simula el comportamiento de un flip flop D
//,de flancos ascedentes,con reset asincronico
module RisingEdgeFlipFlopD(
D,
Q,
clk,
reset_n
);

input D; // Data input 
input clk; // clock input 
input reset_n; //reset input
output reg Q; // output Q 
always @(posedge clk) 
begin
 Q <= D; 
end 

always @(reset_n) //Si reset_n es 0, pone en cero la salida del flip flop
    if (~reset_n) begin
      Q<=0;
    end

endmodule

ej3/Mealy3/src/FSM.v
//Modulo que simula una maquina de estados de Mealy con
//dos estados. La misma puede ser implementada como un
//detector de flancos ascendentes.


module FSM(
    w,
    z,
    clk,
    reset_n
);
input clk; //Entrada de clock
input reset_n; //Entrada de reset
input w; //entrada de la FSM
output z; //salida de la FSM
wire estado_actual;
wire prox_estado = w;

RisingEdgeFlipFlopD f1(prox_estado,estado_actual,clk,reset_n);
logica_comb_de_salida segundo_bloque(w,estado_actual,z);

endmodule

Mealy3/src/FSM_tb.v
//Testbench correspondiente a la FSM que implementa el control
//de dos bombas de agua.
`timescale 10us / 1us

module FSM_tb;

wire clk;
reg reset_n;
reg w;
wire z;
FSM inst(w,z,clk,reset_n);
clock_gen clk_gen(clk);

initial begin
    reset_n=0; //Pongo la FSM en su estado incial
    w=0;
    #1
    reset_n=1;
    #1
    w=1;
    #2
    w=0;
    #2
    w=1;
    #3
    w=0;
    #1
    $finish;

end

reg dummy;
  reg[8*64:0] dumpfile_path = "output.vcd";

  initial begin
    dummy = $value$plusargs("VCD_PATH=%s", dumpfile_path);
    $dumpfile(dumpfile_path);
    $dumpvars(0,FSM_tb);
  end


endmodule

Mealy3/bin/output.vcd
$date
	Sun Nov  4 11:52:03 2018
$end
$version
	Icarus Verilog
$end
$timescale
	1us
$end
$scope module FSM_tb $end
$var wire 1 ! clk $end
$var wire 1 " z $end
$var reg 1 # dummy $end
$var reg 513 $ dumpfile_path [512:0] $end
$var reg 1 % reset_n $end
$var reg 1 & w $end
$scope module inst $end
$var wire 1 ! clk $end
$var wire 1 ' estado_actual $end
$var wire 1 ( prox_estado $end
$var wire 1 ) reset_n $end
$var wire 1 * w $end
$var wire 1 " z $end
$scope module f1 $end
$var wire 1 ( D $end
$var wire 1 ! clk $end
$var wire 1 ) reset_n $end
$var reg 1 + Q $end
$upscope $end
$scope module segundo_bloque $end
$var wire 1 , a $end
$var wire 1 - b $end
$var wire 1 * w $end
$var wire 1 ' y $end
$var wire 1 " z $end
$upscope $end
$upscope $end
$scope module clk_gen $end
$var reg 1 . clk $end
$scope begin CLOCK_DRIVER $end
$upscope $end
$upscope $end
$upscope $end
$enddefinitions $end
#0
$dumpvars
0.
1-
1,
0+
0*
0)
0(
0'
0&
0%
b110001001101001011011100010111101101111011101010111010001110000011101010111010000101110011101100110001101100100 $
1#
0"
0!
$end
#5
1.
1!
#10
0.
0!
1%
1)
#15
1.
1!
#20
0.
0!
1"
0-
1&
1(
1*
#25
0"
1-
0,
1+
1'
1.
1!
#30
0.
0!
#35
1.
1!
#40
0.
0!
0&
0(
0*
#45
1,
0+
0'
1.
1!
#50
0.
0!
#55
1.
1!
#60
0.
0!
1"
0-
1&
1(
1*
#65
0"
1-
0,
1+
1'
1.
1!
#70
0.
0!
#75
1.
1!
#80
0.
0!
#85
1.
1!
#90
0.
0!
0&
0(
0*
#95
1,
0+
0'
1.
1!
