ej3/Moore3/Moore/clock.v
`timescale 100us/100us

module clock_gen(clk);

	parameter PERIOD = 10;

	output reg clk;
		
	always
		begin: CLOCK_DRIVER
			clk <= 1'b0;
			#(PERIOD/2);
			clk <= 1'b1;
			#(PERIOD/2);
		end

endmodule

ej 1/Mealy/src/logica_comb_de_salida.v
//Modulo que se encarga de la logica combinacional del bloque
//de salida de la maquina de estados.
//Este es el bloque que define cual va a ser la salida
//de la FSM en base al estado actual y a los inputs de los
//sensores de los niveles de agua.
module logica_comb_de_salida(
    I,
    S,
    y,
    B1,
    B2
);

input I;
input S;
input y;
output B1;
output B2;
wire a,b,c,d;
nand (a,S,S); //Niego s
nand (b,y,y); //Niego y
nand(c,a,b);
nand(B1,c,I);

nand (d,a,y);
nand(B2,I,d);

endmodule

ej3/Mealy3/src/RisingEdgeFlipFlopD.v
//Modulo que simula el comportamiento de un flip flop D
//,de flancos ascedentes,con reset asincronico
module RisingEdgeFlipFlopD(
D,
Q,
clk,
reset_n
);

input D; // Data input 
input clk; // clock input 
input reset_n; //reset input
output reg Q; // output Q 
always @(posedge clk) 
begin
 Q <= D; 
end 

always @(reset_n) //Si reset_n es 0, pone en cero la salida del flip flop
    if (~reset_n) begin
      Q<=0;
    end

endmodule

ej1/Mealy/src/logica_comb_de_entrada.v
//Modulo que se encarga de la logica combinacional del bloque
//de entrada de la maquina de estados.
//Este es el bloque que define cual va a ser el proximo estado
//de la FSM en base al estado actual y a los inputs de los
//sensores de los niveles de agua.
module logica_comb_de_entrada(
    I,
    S,
    y,
    Yout
);

input I;
input S;
input y;
output Yout;
wire a;
nand (a,S,S); //Utilizo una nand como not
nand (Yout, I, a, y);

endmodule

ej1/Mealy/src/ControlBombaAgua.v
//Modulo que simula el control de una bomba de
//agua que funciona con dos sensores.
module ControlBombaAgua(
    I,
    S,
    B1,
    B2,
    clk,
    reset_n
);
input clk; //Entrada de clock
input reset_n; //Entrada de reset
input I; //Sensor del nivel inferior de la bomba
input S; //Sensor del nivel superior de la bomba
output B1;
output B2;
wire estado_actual;
wire prox_estado;

logica_comb_de_entrada primer_bloque(I,S,estado_actual,prox_estado);
RisingEdgeFlipFlopD f1(prox_estado,estado_actual,clk,reset_n);
logica_comb_de_salida segundo_bloque(I,S,estado_actual,B1,B2);

endmodule // ControlBombaAgua

ej1/Mealy/src/ControlBombaAgua_tb.v
//Testbench correspondiente a la FSM que implementa el control
//de dos bombas de agua.
`timescale 10us / 1us

module ControlBombaAgua_tb;

wire clk;
reg reset_n;
reg I;
reg S;
wire B1;
wire B2;
ControlBombaAgua inst(I,S,B1,B2,clk,reset_n);
clock_gen clk_gen(clk);

initial begin
    reset_n=0; //Pongo la FSM en su estado incial
    I=0;
    S=0;
    #1
    reset_n=1;
    #1
    I=1;
    S=0;
    #2
    I=1;
    S=1;
    #2
    I=1;
    S=0;
    #2
    I=1;
    S=1;
    #1
    $finish;

end

reg dummy;
  reg[8*64:0] dumpfile_path = "output.vcd";

  initial begin
    dummy = $value$plusargs("VCD_PATH=%s", dumpfile_path);
    $dumpfile(dumpfile_path);
    $dumpvars(0,ControlBombaAgua_tb);
  end


endmodule

ej 1/Mealy/bin/output.vcd
$date
	Sun Nov  4 11:24:06 2018
$end
$version
	Icarus Verilog
$end
$timescale
	1us
$end
$scope module ControlBombaAgua_tb $end
$var wire 1 ! B1 $end
$var wire 1 " B2 $end
$var wire 1 # clk $end
$var reg 1 $ I $end
$var reg 1 % S $end
$var reg 1 & dummy $end
$var reg 513 ' dumpfile_path [512:0] $end
$var reg 1 ( reset_n $end
$scope module inst $end
$var wire 1 ! B1 $end
$var wire 1 " B2 $end
$var wire 1 ) I $end
$var wire 1 * S $end
$var wire 1 # clk $end
$var wire 1 + estado_actual $end
$var wire 1 , prox_estado $end
$var wire 1 - reset_n $end
$scope module primer_bloque $end
$var wire 1 ) I $end
$var wire 1 * S $end
$var wire 1 , Yout $end
$var wire 1 . a $end
$var wire 1 + y $end
$upscope $end
$scope module f1 $end
$var wire 1 , D $end
$var wire 1 # clk $end
$var wire 1 - reset_n $end
$var reg 1 / Q $end
$upscope $end
$scope module segundo_bloque $end
$var wire 1 ! B1 $end
$var wire 1 " B2 $end
$var wire 1 ) I $end
$var wire 1 * S $end
$var wire 1 0 a $end
$var wire 1 1 b $end
$var wire 1 2 c $end
$var wire 1 3 d $end
$var wire 1 + y $end
$upscope $end
$upscope $end
$scope module clk_gen $end
$var reg 1 4 clk $end
$scope begin CLOCK_DRIVER $end
$upscope $end
$upscope $end
$upscope $end
$enddefinitions $end
#0
$dumpvars
04
13
02
11
10
0/
1.
0-
1,
0+
0*
0)
0(
b110001001101001011011100010111101101111011101010111010001110000011101010111010000101110011101100110001101100100 '
1&
0%
0$
0#
1"
1!
$end
#5
12
01
03
1/
1+
14
1#
#10
04
0#
1(
1-
#15
14
1#
#20
04
0#
0,
0!
1$
1)
#25
1!
02
0"
11
13
1,
0/
0+
14
1#
#30
04
0#
#35
0!
12
1"
01
03
0,
1/
1+
14
1#
#40
04
0#
0"
1,
13
0.
00
1%
1*
#45
14
1#
#50
04
0#
#55
14
1#
#60
04
0#
1"
0,
03
1.
10
0%
0*
#65
1!
02
0"
11
13
1,
0/
0+
14
1#
#70
04
0#
#75
0!
12
1"
01
03
0,
1/
1+
14
1#
#80
04
0#
0"
1,
13
0.
00
1%
1*
